metadata/__init__.py
metadata/devices.py
metadata/names.py
ameise_ad_dataset-0.1.dist-info/LICENSE
ameise_ad_dataset-0.1.dist-info/METADATA
ameise_ad_dataset-0.1.dist-info/WHEEL
ameise_ad_dataset-0.1.dist-info/top_level.txt
ameise_ad_dataset-0.1.dist-info/RECORD
