Metadata-Version: 2.1
Name: ameise-ad-dataset
Version: 0.1
Summary: Dev-Kit for AMEISE dataset
Home-page: https://github.com/MarcelVSHNS/ameise-dataset.git
Author: Marcel
Author-email: marcel.vosshans@hs-esslingen.de
License: Apache License 2.0
License-File: LICENSE
Requires-Dist: numpy
Requires-Dist: dill
